tornamona/__init__.py
tornamona/cli.py
tornamona/fixes/__init__.py
tornamona/fixes/nisra.py
tornamona-0.1.2.dist-info/AUTHORS.rst
tornamona-0.1.2.dist-info/LICENSE
tornamona-0.1.2.dist-info/METADATA
tornamona-0.1.2.dist-info/WHEEL
tornamona-0.1.2.dist-info/entry_points.txt
tornamona-0.1.2.dist-info/top_level.txt
tornamona-0.1.2.dist-info/RECORD
