Metadata-Version: 2.1
Name: tornamona
Version: 0.1.2
Summary: A series of fixes for Data originating from Northern Ireland
Home-page: https://github.com/andrewbolster/tornamona
Author: Andrew Bolster
Author-email: me@andrewbolster.info
License: UNKNOWN
Keywords: tornamona
Platform: UNKNOWN
Classifier: Development Status :: 2 - Pre-Alpha
Classifier: Intended Audience :: Developers
Classifier: Natural Language :: English
Classifier: Programming Language :: Python :: 3
Classifier: Programming Language :: Python :: 3.6
Classifier: Programming Language :: Python :: 3.7
Classifier: Programming Language :: Python :: 3.8
Requires-Python: >=3.6
Requires-Dist: Click (>=7.0)
Requires-Dist: pandas (>=0.24)
Requires-Dist: xlrd (>=1.0)
Requires-Dist: tqdm (>=4)
Requires-Dist: tabulate
